pip_check_reqs/__init__.py
pip_check_reqs/common.py
pip_check_reqs/find_extra_reqs.py
pip_check_reqs/find_missing_reqs.py
pip_check_reqs-2.5.4.dist-info/licenses/LICENSE
pip_check_reqs-2.5.4.dist-info/METADATA
pip_check_reqs-2.5.4.dist-info/WHEEL
pip_check_reqs-2.5.4.dist-info/entry_points.txt
pip_check_reqs-2.5.4.dist-info/top_level.txt
pip_check_reqs-2.5.4.dist-info/RECORD
