Metadata-Version: 2.4
Name: pip-check-reqs
Version: 2.5.4
Summary: Find packages that should or should not be in requirements for a project
Author-email: Adam Dangoor <adamdangoor@gmail.com>, Richard Jones <r1chardj0n3s@gmail.com>
Maintainer-email: Adam Dangoor <adamdangoor@gmail.com>, Richard Jones <r1chardj0n3s@gmail.com>
License: The MIT License (MIT)
Project-URL: Changelog, https://github.com/r1chardj0n3s/pip-check-reqs/blob/master/CHANGELOG.rst
Project-URL: Homepage, https://github.com/r1chardj0n3s/pip-check-reqs
Keywords: lint,pip
Classifier: Development Status :: 5 - Production/Stable
Classifier: Intended Audience :: Developers
Classifier: License :: OSI Approved :: MIT License
Classifier: Operating System :: Microsoft :: Windows
Classifier: Operating System :: POSIX
Classifier: Programming Language :: Python :: 3 :: Only
Classifier: Programming Language :: Python :: 3.9
Classifier: Programming Language :: Python :: 3.10
Classifier: Programming Language :: Python :: 3.11
Classifier: Programming Language :: Python :: 3.12
Classifier: Programming Language :: Python :: 3.13
Classifier: Topic :: Software Development :: Build Tools
Requires-Python: >=3.9
License-File: LICENSE
Requires-Dist: packaging>=22
Requires-Dist: pip>=23.2
Provides-Extra: dev
Requires-Dist: actionlint-py==1.7.7.23; extra == "dev"
Requires-Dist: mypy==1.15.0; extra == "dev"
Requires-Dist: pyenchant==3.2.2; extra == "dev"
Requires-Dist: pylint==3.3.7; extra == "dev"
Requires-Dist: pyproject-fmt==2.6.0; extra == "dev"
Requires-Dist: pyright==1.1.397; extra == "dev"
Requires-Dist: pyroma==4.2; extra == "dev"
Requires-Dist: pytest==8.3.5; extra == "dev"
Requires-Dist: pytest-cov==6.1.1; extra == "dev"
Requires-Dist: ruamel.yaml==0.18.10; extra == "dev"
Requires-Dist: ruff==0.11.10; extra == "dev"
Dynamic: license-file
